powernovo/__init__.py
powernovo/inference.py
powernovo/run.py
powernovo/beam_search/__init__.py
powernovo/beam_search/adaptive_beam_search.py
powernovo/beam_search/bert_hypotheses_search.py
powernovo/depthcharge_base/__init__.py
powernovo/depthcharge_base/data/__init__.py
powernovo/depthcharge_base/data/parsers.py
powernovo/depthcharge_base/data/peptide_datasets.py
powernovo/depthcharge_base/data/preprocessing.py
powernovo/depthcharge_base/data/spectrum_datasets.py
powernovo/depthcharge_base/encoders/__init__.py
powernovo/depthcharge_base/encoders/sinusoidal.py
powernovo/depthcharge_base/tokenizers/__init__.py
powernovo/depthcharge_base/tokenizers/peptides.py
powernovo/depthcharge_base/tokenizers/tokenizer.py
powernovo/depthcharge_base/transformers/__init__.py
powernovo/depthcharge_base/transformers/peptides.py
powernovo/depthcharge_base/transformers/spectra.py
powernovo/depthcharge_base/utils/__init__.py
powernovo/depthcharge_base/utils/constants.py
powernovo/depthcharge_base/utils/feedforward.py
powernovo/depthcharge_base/utils/primitives.py
powernovo/depthcharge_base/utils/utils.py
powernovo/models/__init__.py
powernovo/models/peptide_bert/__init__.py
powernovo/models/peptide_bert/peptide_bert.py
powernovo/models/spectrum/__init__.py
powernovo/models/spectrum/spectrum_inference.py
powernovo/peptides/__init__.py
powernovo/peptides/peptide_aggregator.py
powernovo/pipeline_config/__init__.py
powernovo/pipeline_config/config.py
powernovo/proteins/__init__.py
powernovo/proteins/greedy_solver.py
powernovo/proteins/output_builder.py
powernovo/proteins/protein_inference.py
powernovo/proteins/protein_merger.py
powernovo/proteins/psm_network.py
powernovo/proteins/sequences_tagger.py
powernovo/utils/__init__.py
powernovo/utils/utils.py
powernovo-1.0.17.dist-info/LICENSE
powernovo-1.0.17.dist-info/METADATA
powernovo-1.0.17.dist-info/WHEEL
powernovo-1.0.17.dist-info/top_level.txt
powernovo-1.0.17.dist-info/RECORD
