Metadata-Version: 2.1
Name: powernovo
Version: 1.0.17
Summary: PowerNovo: A New Efficient Tool for De Novo Peptide Sequencing
Home-page: https://github.com/protdb/PowerNovo
Author: Denis Petrovskiy
Author-email: petro2017@mail.ru
License: MIT
Platform: UNKNOWN
License-File: LICENSE
Requires-Dist: torch (>=2.0.1)
Requires-Dist: numpy (~=1.26.3)
Requires-Dist: transformers (~=4.36.2)
Requires-Dist: requests (~=2.31.0)
Requires-Dist: pandas (~=2.1.4)
Requires-Dist: npysearch (~=1.3.1)
Requires-Dist: networkx (~=3.2.1)
Requires-Dist: deap (~=1.4.1)
Requires-Dist: tqdm (~=4.66.1)
Requires-Dist: PyYAML (~=6.0.1)
Requires-Dist: pyteomics (~=4.6.3)
Requires-Dist: dill (~=0.3.7)
Requires-Dist: h5py (~=3.10.0)
Requires-Dist: selfies (~=2.1.1)
Requires-Dist: rdkit (~=2023.9.4)
Requires-Dist: einops (~=0.7.0)
Requires-Dist: numba (~=0.58.1)
Requires-Dist: spectrum-utils
Requires-Dist: biopython
Requires-Dist: lxml
Requires-Dist: sortedcontainers (~=2.4.0)
